{
	"data": [
		{
			"id": 29101,
			"group": 1101,
			"stageId": 29101,
			"o_HMJOGHLAMHP": [
				0
			],
			"o_EKGIOMIPJFG": [
				0
			],
			"o_PPCLPIGIEDG": [
				0
			],
			"o_PLBGPCHBKGB": [
				0
			],
			"o_JODHDFMANLK": [
				0
			],
			"o_FHDEGGLEOKD": [
				0
			]
		},
		{
			"id": 29102,
			"group": 1102,
			"stageId": 29102,
			"o_HMJOGHLAMHP": [
				0
			],
			"o_EKGIOMIPJFG": [
				0
			],
			"o_PPCLPIGIEDG": [
				0
			],
			"o_PLBGPCHBKGB": [
				0
			],
			"o_JODHDFMANLK": [
				0
			],
			"o_FHDEGGLEOKD": [
				0
			]
		},
		{
			"id": 29111,
			"group": 1201,
			"stageId": 29111,
			"o_HMJOGHLAMHP": [
				0
			],
			"o_EKGIOMIPJFG": [
				0
			],
			"o_PPCLPIGIEDG": [
				0
			],
			"o_PLBGPCHBKGB": [
				0
			],
			"o_JODHDFMANLK": [
				0
			],
			"o_FHDEGGLEOKD": [
				0
			]
		},
		{
			"id": 29112,
			"group": 1202,
			"stageId": 29112,
			"o_HMJOGHLAMHP": [
				0
			],
			"o_EKGIOMIPJFG": [
				0
			],
			"o_PPCLPIGIEDG": [
				0
			],
			"o_PLBGPCHBKGB": [
				0
			],
			"o_JODHDFMANLK": [
				0
			],
			"o_FHDEGGLEOKD": [
				0
			]
		},
		{
			"id": 29121,
			"group": 1301,
			"stageId": 29121,
			"o_HMJOGHLAMHP": [
				0
			],
			"o_EKGIOMIPJFG": [
				0
			],
			"o_PPCLPIGIEDG": [
				0
			],
			"o_PLBGPCHBKGB": [
				0
			],
			"o_JODHDFMANLK": [
				0
			],
			"o_FHDEGGLEOKD": [
				0
			]
		},
		{
			"id": 29122,
			"group": 1302,
			"stageId": 29122,
			"o_HMJOGHLAMHP": [
				0
			],
			"o_EKGIOMIPJFG": [
				0
			],
			"o_PPCLPIGIEDG": [
				0
			],
			"o_PLBGPCHBKGB": [
				0
			],
			"o_JODHDFMANLK": [
				0
			],
			"o_FHDEGGLEOKD": [
				0
			]
		},
		{
			"id": 29123,
			"group": 1303,
			"stageId": 29122,
			"o_HMJOGHLAMHP": [
				0
			],
			"o_EKGIOMIPJFG": [
				0
			],
			"o_PPCLPIGIEDG": [
				0
			],
			"o_PLBGPCHBKGB": [
				0
			],
			"o_JODHDFMANLK": [
				0
			],
			"o_FHDEGGLEOKD": [
				0
			]
		},
		{
			"id": 29131,
			"group": 1401,
			"stageId": 29131,
			"o_HMJOGHLAMHP": [
				0
			],
			"o_EKGIOMIPJFG": [
				0
			],
			"o_PPCLPIGIEDG": [
				0
			],
			"o_PLBGPCHBKGB": [
				0
			],
			"o_JODHDFMANLK": [
				0
			],
			"o_FHDEGGLEOKD": [
				0
			]
		},
		{
			"id": 29132,
			"group": 1402,
			"stageId": 29132,
			"o_HMJOGHLAMHP": [
				0
			],
			"o_EKGIOMIPJFG": [
				0
			],
			"o_PPCLPIGIEDG": [
				0
			],
			"o_PLBGPCHBKGB": [
				0
			],
			"o_JODHDFMANLK": [
				0
			],
			"o_FHDEGGLEOKD": [
				0
			]
		},
		{
			"id": 29133,
			"group": 1403,
			"stageId": 29132,
			"o_HMJOGHLAMHP": [
				0
			],
			"o_EKGIOMIPJFG": [
				0
			],
			"o_PPCLPIGIEDG": [
				0
			],
			"o_PLBGPCHBKGB": [
				0
			],
			"o_JODHDFMANLK": [
				0
			],
			"o_FHDEGGLEOKD": [
				0
			]
		},
		{
			"id": 29171,
			"group": 1501,
			"stageId": 29171,
			"o_HMJOGHLAMHP": [
				0
			],
			"o_EKGIOMIPJFG": [
				0
			],
			"o_PPCLPIGIEDG": [
				0
			],
			"o_PLBGPCHBKGB": [
				0
			],
			"o_JODHDFMANLK": [
				0
			],
			"o_FHDEGGLEOKD": [
				0
			]
		},
		{
			"id": 29211,
			"group": 2101,
			"stageId": 29211,
			"o_HMJOGHLAMHP": [
				0
			],
			"o_EKGIOMIPJFG": [
				0
			],
			"o_PPCLPIGIEDG": [
				0
			],
			"o_PLBGPCHBKGB": [
				0
			],
			"o_JODHDFMANLK": [
				0
			],
			"o_FHDEGGLEOKD": [
				0
			]
		},
		{
			"id": 29212,
			"group": 2102,
			"stageId": 29212,
			"o_HMJOGHLAMHP": [
				0
			],
			"o_EKGIOMIPJFG": [
				0
			],
			"o_PPCLPIGIEDG": [
				0
			],
			"o_PLBGPCHBKGB": [
				0
			],
			"o_JODHDFMANLK": [
				0
			],
			"o_FHDEGGLEOKD": [
				0
			]
		},
		{
			"id": 29221,
			"group": 2201,
			"stageId": 29221,
			"o_HMJOGHLAMHP": [
				0
			],
			"o_EKGIOMIPJFG": [
				0
			],
			"o_PPCLPIGIEDG": [
				0
			],
			"o_PLBGPCHBKGB": [
				0
			],
			"o_JODHDFMANLK": [
				0
			],
			"o_FHDEGGLEOKD": [
				0
			]
		},
		{
			"id": 29222,
			"group": 2202,
			"stageId": 29222,
			"o_HMJOGHLAMHP": [
				0
			],
			"o_EKGIOMIPJFG": [
				0
			],
			"o_PPCLPIGIEDG": [
				0
			],
			"o_PLBGPCHBKGB": [
				0
			],
			"o_JODHDFMANLK": [
				0
			],
			"o_FHDEGGLEOKD": [
				0
			]
		},
		{
			"id": 29231,
			"group": 2301,
			"stageId": 29231,
			"o_HMJOGHLAMHP": [
				0
			],
			"o_EKGIOMIPJFG": [
				0
			],
			"o_PPCLPIGIEDG": [
				0
			],
			"o_PLBGPCHBKGB": [
				0
			],
			"o_JODHDFMANLK": [
				0
			],
			"o_FHDEGGLEOKD": [
				0
			]
		},
		{
			"id": 29232,
			"group": 2302,
			"stageId": 29232,
			"o_HMJOGHLAMHP": [
				0
			],
			"o_EKGIOMIPJFG": [
				0
			],
			"o_PPCLPIGIEDG": [
				0
			],
			"o_PLBGPCHBKGB": [
				0
			],
			"o_JODHDFMANLK": [
				0
			],
			"o_FHDEGGLEOKD": [
				0
			]
		},
		{
			"id": 29233,
			"group": 2303,
			"stageId": 29233,
			"o_HMJOGHLAMHP": [
				0
			],
			"o_EKGIOMIPJFG": [
				0
			],
			"o_PPCLPIGIEDG": [
				0
			],
			"o_PLBGPCHBKGB": [
				0
			],
			"o_JODHDFMANLK": [
				0
			],
			"o_FHDEGGLEOKD": [
				0
			]
		},
		{
			"id": 29241,
			"group": 2401,
			"stageId": 29241,
			"o_HMJOGHLAMHP": [
				0
			],
			"o_EKGIOMIPJFG": [
				0
			],
			"o_PPCLPIGIEDG": [
				0
			],
			"o_PLBGPCHBKGB": [
				0
			],
			"o_JODHDFMANLK": [
				0
			],
			"o_FHDEGGLEOKD": [
				0
			]
		},
		{
			"id": 29242,
			"group": 2402,
			"stageId": 29242,
			"o_HMJOGHLAMHP": [
				0
			],
			"o_EKGIOMIPJFG": [
				0
			],
			"o_PPCLPIGIEDG": [
				0
			],
			"o_PLBGPCHBKGB": [
				0
			],
			"o_JODHDFMANLK": [
				0
			],
			"o_FHDEGGLEOKD": [
				0
			]
		},
		{
			"id": 29243,
			"group": 2403,
			"stageId": 29243,
			"o_HMJOGHLAMHP": [
				0
			],
			"o_EKGIOMIPJFG": [
				0
			],
			"o_PPCLPIGIEDG": [
				0
			],
			"o_PLBGPCHBKGB": [
				0
			],
			"o_JODHDFMANLK": [
				0
			],
			"o_FHDEGGLEOKD": [
				0
			]
		},
		{
			"id": 29271,
			"group": 2501,
			"stageId": 29271,
			"o_HMJOGHLAMHP": [
				0
			],
			"o_EKGIOMIPJFG": [
				0
			],
			"o_PPCLPIGIEDG": [
				0
			],
			"o_PLBGPCHBKGB": [
				0
			],
			"o_JODHDFMANLK": [
				0
			],
			"o_FHDEGGLEOKD": [
				0
			]
		},
		{
			"id": 29311,
			"group": 3101,
			"stageId": 29311,
			"o_HMJOGHLAMHP": [
				0
			],
			"o_EKGIOMIPJFG": [
				0
			],
			"o_PPCLPIGIEDG": [
				0
			],
			"o_PLBGPCHBKGB": [
				0
			],
			"o_JODHDFMANLK": [
				0
			],
			"o_FHDEGGLEOKD": [
				0
			]
		},
		{
			"id": 29312,
			"group": 3102,
			"stageId": 29312,
			"o_HMJOGHLAMHP": [
				0
			],
			"o_EKGIOMIPJFG": [
				0
			],
			"o_PPCLPIGIEDG": [
				0
			],
			"o_PLBGPCHBKGB": [
				0
			],
			"o_JODHDFMANLK": [
				0
			],
			"o_FHDEGGLEOKD": [
				0
			]
		},
		{
			"id": 29321,
			"group": 3201,
			"stageId": 29321,
			"o_HMJOGHLAMHP": [
				0
			],
			"o_EKGIOMIPJFG": [
				0
			],
			"o_PPCLPIGIEDG": [
				0
			],
			"o_PLBGPCHBKGB": [
				0
			],
			"o_JODHDFMANLK": [
				0
			],
			"o_FHDEGGLEOKD": [
				0
			]
		},
		{
			"id": 29322,
			"group": 3202,
			"stageId": 29322,
			"o_HMJOGHLAMHP": [
				0
			],
			"o_EKGIOMIPJFG": [
				0
			],
			"o_PPCLPIGIEDG": [
				0
			],
			"o_PLBGPCHBKGB": [
				0
			],
			"o_JODHDFMANLK": [
				0
			],
			"o_FHDEGGLEOKD": [
				0
			]
		},
		{
			"id": 29331,
			"group": 3301,
			"stageId": 29331,
			"o_HMJOGHLAMHP": [
				0
			],
			"o_EKGIOMIPJFG": [
				0
			],
			"o_PPCLPIGIEDG": [
				0
			],
			"o_PLBGPCHBKGB": [
				0
			],
			"o_JODHDFMANLK": [
				0
			],
			"o_FHDEGGLEOKD": [
				0
			]
		},
		{
			"id": 29332,
			"group": 3302,
			"stageId": 29332,
			"o_HMJOGHLAMHP": [
				0
			],
			"o_EKGIOMIPJFG": [
				0
			],
			"o_PPCLPIGIEDG": [
				0
			],
			"o_PLBGPCHBKGB": [
				0
			],
			"o_JODHDFMANLK": [
				0
			],
			"o_FHDEGGLEOKD": [
				0
			]
		},
		{
			"id": 29333,
			"group": 3303,
			"stageId": 29333,
			"o_HMJOGHLAMHP": [
				0
			],
			"o_EKGIOMIPJFG": [
				0
			],
			"o_PPCLPIGIEDG": [
				0
			],
			"o_PLBGPCHBKGB": [
				0
			],
			"o_JODHDFMANLK": [
				0
			],
			"o_FHDEGGLEOKD": [
				0
			]
		},
		{
			"id": 29341,
			"group": 3401,
			"stageId": 29341,
			"o_HMJOGHLAMHP": [
				0
			],
			"o_EKGIOMIPJFG": [
				0
			],
			"o_PPCLPIGIEDG": [
				0
			],
			"o_PLBGPCHBKGB": [
				0
			],
			"o_JODHDFMANLK": [
				0
			],
			"o_FHDEGGLEOKD": [
				0
			]
		},
		{
			"id": 29342,
			"group": 3402,
			"stageId": 29342,
			"o_HMJOGHLAMHP": [
				0
			],
			"o_EKGIOMIPJFG": [
				0
			],
			"o_PPCLPIGIEDG": [
				0
			],
			"o_PLBGPCHBKGB": [
				0
			],
			"o_JODHDFMANLK": [
				0
			],
			"o_FHDEGGLEOKD": [
				0
			]
		},
		{
			"id": 29343,
			"group": 3403,
			"stageId": 29343,
			"o_HMJOGHLAMHP": [
				0
			],
			"o_EKGIOMIPJFG": [
				0
			],
			"o_PPCLPIGIEDG": [
				0
			],
			"o_PLBGPCHBKGB": [
				0
			],
			"o_JODHDFMANLK": [
				0
			],
			"o_FHDEGGLEOKD": [
				0
			]
		},
		{
			"id": 29371,
			"group": 3501,
			"stageId": 29371,
			"o_HMJOGHLAMHP": [
				0
			],
			"o_EKGIOMIPJFG": [
				0
			],
			"o_PPCLPIGIEDG": [
				0
			],
			"o_PLBGPCHBKGB": [
				0
			],
			"o_JODHDFMANLK": [
				0
			],
			"o_FHDEGGLEOKD": [
				0
			]
		},
		{
			"id": 29411,
			"group": 4101,
			"stageId": 29411,
			"o_HMJOGHLAMHP": [
				0
			],
			"o_EKGIOMIPJFG": [
				0
			],
			"o_PPCLPIGIEDG": [
				0
			],
			"o_PLBGPCHBKGB": [
				0
			],
			"o_JODHDFMANLK": [
				0
			],
			"o_FHDEGGLEOKD": [
				0
			]
		},
		{
			"id": 29412,
			"group": 4102,
			"stageId": 29412,
			"o_HMJOGHLAMHP": [
				0
			],
			"o_EKGIOMIPJFG": [
				0
			],
			"o_PPCLPIGIEDG": [
				0
			],
			"o_PLBGPCHBKGB": [
				0
			],
			"o_JODHDFMANLK": [
				0
			],
			"o_FHDEGGLEOKD": [
				0
			]
		},
		{
			"id": 29421,
			"group": 4201,
			"stageId": 29421,
			"o_HMJOGHLAMHP": [
				0
			],
			"o_EKGIOMIPJFG": [
				0
			],
			"o_PPCLPIGIEDG": [
				0
			],
			"o_PLBGPCHBKGB": [
				0
			],
			"o_JODHDFMANLK": [
				0
			],
			"o_FHDEGGLEOKD": [
				0
			]
		},
		{
			"id": 29422,
			"group": 4202,
			"stageId": 29422,
			"o_HMJOGHLAMHP": [
				0
			],
			"o_EKGIOMIPJFG": [
				0
			],
			"o_PPCLPIGIEDG": [
				0
			],
			"o_PLBGPCHBKGB": [
				0
			],
			"o_JODHDFMANLK": [
				0
			],
			"o_FHDEGGLEOKD": [
				0
			]
		},
		{
			"id": 29431,
			"group": 4301,
			"stageId": 29431,
			"o_HMJOGHLAMHP": [
				0
			],
			"o_EKGIOMIPJFG": [
				0
			],
			"o_PPCLPIGIEDG": [
				0
			],
			"o_PLBGPCHBKGB": [
				0
			],
			"o_JODHDFMANLK": [
				0
			],
			"o_FHDEGGLEOKD": [
				0
			]
		},
		{
			"id": 29432,
			"group": 4302,
			"stageId": 29432,
			"o_HMJOGHLAMHP": [
				0
			],
			"o_EKGIOMIPJFG": [
				0
			],
			"o_PPCLPIGIEDG": [
				0
			],
			"o_PLBGPCHBKGB": [
				0
			],
			"o_JODHDFMANLK": [
				0
			],
			"o_FHDEGGLEOKD": [
				0
			]
		},
		{
			"id": 29433,
			"group": 4303,
			"stageId": 29433,
			"o_HMJOGHLAMHP": [
				0
			],
			"o_EKGIOMIPJFG": [
				0
			],
			"o_PPCLPIGIEDG": [
				0
			],
			"o_PLBGPCHBKGB": [
				0
			],
			"o_JODHDFMANLK": [
				0
			],
			"o_FHDEGGLEOKD": [
				0
			]
		},
		{
			"id": 29441,
			"group": 4401,
			"stageId": 29441,
			"o_HMJOGHLAMHP": [
				0
			],
			"o_EKGIOMIPJFG": [
				0
			],
			"o_PPCLPIGIEDG": [
				0
			],
			"o_PLBGPCHBKGB": [
				0
			],
			"o_JODHDFMANLK": [
				0
			],
			"o_FHDEGGLEOKD": [
				0
			]
		},
		{
			"id": 29442,
			"group": 4402,
			"stageId": 29442,
			"o_HMJOGHLAMHP": [
				0
			],
			"o_EKGIOMIPJFG": [
				0
			],
			"o_PPCLPIGIEDG": [
				0
			],
			"o_PLBGPCHBKGB": [
				0
			],
			"o_JODHDFMANLK": [
				0
			],
			"o_FHDEGGLEOKD": [
				0
			]
		},
		{
			"id": 29443,
			"group": 4403,
			"stageId": 29443,
			"o_HMJOGHLAMHP": [
				0
			],
			"o_EKGIOMIPJFG": [
				0
			],
			"o_PPCLPIGIEDG": [
				0
			],
			"o_PLBGPCHBKGB": [
				0
			],
			"o_JODHDFMANLK": [
				0
			],
			"o_FHDEGGLEOKD": [
				0
			]
		},
		{
			"id": 29471,
			"group": 4501,
			"stageId": 29471,
			"o_HMJOGHLAMHP": [
				0
			],
			"o_EKGIOMIPJFG": [
				0
			],
			"o_PPCLPIGIEDG": [
				0
			],
			"o_PLBGPCHBKGB": [
				0
			],
			"o_JODHDFMANLK": [
				0
			],
			"o_FHDEGGLEOKD": [
				0
			]
		},
		{
			"id": 29511,
			"group": 5101,
			"stageId": 29511,
			"o_HMJOGHLAMHP": [
				0
			],
			"o_EKGIOMIPJFG": [
				0
			],
			"o_PPCLPIGIEDG": [
				0
			],
			"o_PLBGPCHBKGB": [
				0
			],
			"o_JODHDFMANLK": [
				0
			],
			"o_FHDEGGLEOKD": [
				0
			]
		},
		{
			"id": 29512,
			"group": 5102,
			"stageId": 29512,
			"o_HMJOGHLAMHP": [
				0
			],
			"o_EKGIOMIPJFG": [
				0
			],
			"o_PPCLPIGIEDG": [
				0
			],
			"o_PLBGPCHBKGB": [
				0
			],
			"o_JODHDFMANLK": [
				0
			],
			"o_FHDEGGLEOKD": [
				0
			]
		},
		{
			"id": 29521,
			"group": 5201,
			"stageId": 29521,
			"o_HMJOGHLAMHP": [
				0
			],
			"o_EKGIOMIPJFG": [
				0
			],
			"o_PPCLPIGIEDG": [
				0
			],
			"o_PLBGPCHBKGB": [
				0
			],
			"o_JODHDFMANLK": [
				0
			],
			"o_FHDEGGLEOKD": [
				0
			]
		},
		{
			"id": 29522,
			"group": 5202,
			"stageId": 29522,
			"o_HMJOGHLAMHP": [
				0
			],
			"o_EKGIOMIPJFG": [
				0
			],
			"o_PPCLPIGIEDG": [
				0
			],
			"o_PLBGPCHBKGB": [
				0
			],
			"o_JODHDFMANLK": [
				0
			],
			"o_FHDEGGLEOKD": [
				0
			]
		},
		{
			"id": 29531,
			"group": 5301,
			"stageId": 29531,
			"o_HMJOGHLAMHP": [
				0
			],
			"o_EKGIOMIPJFG": [
				0
			],
			"o_PPCLPIGIEDG": [
				0
			],
			"o_PLBGPCHBKGB": [
				0
			],
			"o_JODHDFMANLK": [
				0
			],
			"o_FHDEGGLEOKD": [
				0
			]
		},
		{
			"id": 29532,
			"group": 5302,
			"stageId": 29532,
			"o_HMJOGHLAMHP": [
				0
			],
			"o_EKGIOMIPJFG": [
				0
			],
			"o_PPCLPIGIEDG": [
				0
			],
			"o_PLBGPCHBKGB": [
				0
			],
			"o_JODHDFMANLK": [
				0
			],
			"o_FHDEGGLEOKD": [
				0
			]
		},
		{
			"id": 29533,
			"group": 5303,
			"stageId": 29533,
			"o_HMJOGHLAMHP": [
				0
			],
			"o_EKGIOMIPJFG": [
				0
			],
			"o_PPCLPIGIEDG": [
				0
			],
			"o_PLBGPCHBKGB": [
				0
			],
			"o_JODHDFMANLK": [
				0
			],
			"o_FHDEGGLEOKD": [
				0
			]
		},
		{
			"id": 29541,
			"group": 5401,
			"stageId": 29541,
			"o_HMJOGHLAMHP": [
				0
			],
			"o_EKGIOMIPJFG": [
				0
			],
			"o_PPCLPIGIEDG": [
				0
			],
			"o_PLBGPCHBKGB": [
				0
			],
			"o_JODHDFMANLK": [
				0
			],
			"o_FHDEGGLEOKD": [
				0
			]
		},
		{
			"id": 29542,
			"group": 5402,
			"stageId": 29542,
			"o_HMJOGHLAMHP": [
				0
			],
			"o_EKGIOMIPJFG": [
				0
			],
			"o_PPCLPIGIEDG": [
				0
			],
			"o_PLBGPCHBKGB": [
				0
			],
			"o_JODHDFMANLK": [
				0
			],
			"o_FHDEGGLEOKD": [
				0
			]
		},
		{
			"id": 29543,
			"group": 5403,
			"stageId": 29543,
			"o_HMJOGHLAMHP": [
				0
			],
			"o_EKGIOMIPJFG": [
				0
			],
			"o_PPCLPIGIEDG": [
				0
			],
			"o_PLBGPCHBKGB": [
				0
			],
			"o_JODHDFMANLK": [
				0
			],
			"o_FHDEGGLEOKD": [
				0
			]
		},
		{
			"id": 29571,
			"group": 5501,
			"stageId": 29571,
			"o_HMJOGHLAMHP": [
				0
			],
			"o_EKGIOMIPJFG": [
				0
			],
			"o_PPCLPIGIEDG": [
				0
			],
			"o_PLBGPCHBKGB": [
				0
			],
			"o_JODHDFMANLK": [
				0
			],
			"o_FHDEGGLEOKD": [
				0
			]
		}
	]
}