{
	"data": [
		{
			"eventId": 101,
			"nextEvent": [
				106
			],
			"resultList": "1:10011-0",
			"condition": ""
		},
		{
			"eventId": 102,
			"resultList": "1:10012-99",
			"condition": "",
			"nextEvent": []
		},
		{
			"eventId": 103,
			"resultList": "1:10013-99",
			"condition": "",
			"nextEvent": []
		},
		{
			"eventId": 104,
			"resultList": "1:10014-99",
			"condition": "",
			"nextEvent": []
		},
		{
			"eventId": 105,
			"nextEvent": [
				101
			],
			"resultList": "21:105,25:105",
			"condition": ""
		},
		{
			"eventId": 106,
			"condition": "12:1113-0",
			"resultList": "27",
			"nextEvent": []
		},
		{
			"eventId": 107,
			"resultList": "26:47-1-14-4",
			"condition": "",
			"nextEvent": []
		},
		{
			"eventId": 201,
			"resultList": "17:1003",
			"condition": "",
			"nextEvent": []
		},
		{
			"eventId": 202,
			"resultList": "17:1004",
			"condition": "",
			"nextEvent": []
		},
		{
			"eventId": 203,
			"resultList": "17:1005",
			"condition": "",
			"nextEvent": []
		},
		{
			"eventId": 204,
			"resultList": "17:1006",
			"condition": "",
			"nextEvent": []
		},
		{
			"eventId": 9901,
			"nextEvent": [
				9904
			],
			"resultList": "23:99010-0",
			"condition": ""
		},
		{
			"eventId": 9902,
			"nextEvent": [
				9905
			],
			"resultList": "23:99003-0",
			"condition": ""
		},
		{
			"eventId": 9903,
			"nextEvent": [
				9906
			],
			"resultList": "23:99012-0",
			"condition": ""
		},
		{
			"eventId": 9904,
			"condition": "13:99010",
			"resultList": "24:99010-0",
			"nextEvent": []
		},
		{
			"eventId": 9905,
			"condition": "13:99003",
			"resultList": "24:99003-0",
			"nextEvent": []
		},
		{
			"eventId": 9906,
			"condition": "13:99012",
			"resultList": "24:99012-0",
			"nextEvent": []
		},
		{
			"eventId": 90401,
			"nextEvent": [
				90402
			],
			"resultList": "13:904011-0",
			"condition": ""
		},
		{
			"eventId": 90402,
			"condition": "16:904011-1",
			"nextEvent": [
				90403
			],
			"resultList": "14:904011-0,13:904019-0"
		},
		{
			"eventId": 90403,
			"condition": "16:904019-1",
			"nextEvent": [
				90404
			],
			"resultList": "14:904019-0,13:904020-0"
		},
		{
			"eventId": 90404,
			"condition": "16:904020-1",
			"nextEvent": [
				90405
			],
			"resultList": "14:904020-0,13:904021-0"
		},
		{
			"eventId": 90405,
			"condition": "16:904021-1",
			"nextEvent": [
				90406
			],
			"resultList": "14:904021-0,13:904022-0"
		},
		{
			"eventId": 90406,
			"condition": "16:904022-1",
			"resultList": "14:904022-0",
			"nextEvent": []
		},
		{
			"eventId": 90410,
			"nextEvent": [
				90404
			],
			"resultList": "13:904020-0",
			"condition": ""
		},
		{
			"eventId": 90411,
			"nextEvent": [
				90412
			],
			"resultList": "21:105,25:105",
			"condition": ""
		},
		{
			"eventId": 90412,
			"nextEvent": [
				90413
			],
			"resultList": "1:10011-0",
			"condition": ""
		},
		{
			"eventId": 90413,
			"condition": "12:1113-0",
			"resultList": "1:1022-1",
			"nextEvent": []
		},
		{
			"eventId": 90499,
			"condition": "19",
			"resultList": "1:30102-1",
			"nextEvent": []
		},
		{
			"eventId": 90901,
			"nextEvent": [
				90902
			],
			"resultList": "1:10011-0,21:105,25:105,17:1008,1:30403-0,17:1007,1:30303-1,17:2001,1:30102-1",
			"condition": ""
		},
		{
			"eventId": 90902,
			"condition": "19",
			"nextEvent": [
				90902
			],
			"resultList": "1:10011-0,1:30403-0,1:30303-1,1:30102-1"
		},
		{
			"eventId": 99801,
			"resultList": "18:3001,2:30101-1",
			"condition": "",
			"nextEvent": []
		},
		{
			"eventId": 99802,
			"resultList": "18:2001,2:30102-1",
			"condition": "",
			"nextEvent": []
		},
		{
			"eventId": 99803,
			"resultList": "18:1001,2:30103-1",
			"condition": "",
			"nextEvent": []
		},
		{
			"eventId": 99804,
			"resultList": "18:3002",
			"condition": "",
			"nextEvent": []
		},
		{
			"eventId": 99805,
			"resultList": "18:2002",
			"condition": "",
			"nextEvent": []
		},
		{
			"eventId": 99806,
			"resultList": "18:1002",
			"condition": "",
			"nextEvent": []
		},
		{
			"eventId": 99807,
			"resultList": "18:3007,2:30301-1",
			"condition": "",
			"nextEvent": []
		},
		{
			"eventId": 99808,
			"resultList": "18:2007,2:30302-1",
			"condition": "",
			"nextEvent": []
		},
		{
			"eventId": 99809,
			"resultList": "18:1007,2:30303-1",
			"condition": "",
			"nextEvent": []
		},
		{
			"eventId": 99810,
			"resultList": "18:3008,2:30401-0",
			"condition": "",
			"nextEvent": []
		},
		{
			"eventId": 99811,
			"resultList": "18:2008,2:30402-0",
			"condition": "",
			"nextEvent": []
		},
		{
			"eventId": 99812,
			"resultList": "18:1008,2:30403-0",
			"condition": "",
			"nextEvent": []
		},
		{
			"eventId": 99813,
			"resultList": "18:3009",
			"condition": "",
			"nextEvent": []
		},
		{
			"eventId": 99814,
			"resultList": "18:2009",
			"condition": "",
			"nextEvent": []
		},
		{
			"eventId": 99815,
			"resultList": "18:1009",
			"condition": "",
			"nextEvent": []
		},
		{
			"eventId": 99816,
			"resultList": "18:3010",
			"condition": "",
			"nextEvent": []
		},
		{
			"eventId": 99817,
			"resultList": "18:2010",
			"condition": "",
			"nextEvent": []
		},
		{
			"eventId": 99818,
			"resultList": "18:1010",
			"condition": "",
			"nextEvent": []
		},
		{
			"eventId": 99819,
			"resultList": "18:3011,20:30507",
			"condition": "",
			"nextEvent": []
		},
		{
			"eventId": 99820,
			"resultList": "18:2011,20:30508",
			"condition": "",
			"nextEvent": []
		},
		{
			"eventId": 99821,
			"resultList": "18:1011,20:30509",
			"condition": "",
			"nextEvent": []
		},
		{
			"eventId": 99901,
			"resultList": "17:3001,1:30101-1",
			"condition": "",
			"nextEvent": []
		},
		{
			"eventId": 99902,
			"resultList": "17:2001,1:30102-1",
			"condition": "",
			"nextEvent": []
		},
		{
			"eventId": 99903,
			"resultList": "17:1001,1:30103-1",
			"condition": "",
			"nextEvent": []
		},
		{
			"eventId": 99904,
			"resultList": "17:3002",
			"condition": "",
			"nextEvent": []
		},
		{
			"eventId": 99905,
			"resultList": "17:2002",
			"condition": "",
			"nextEvent": []
		},
		{
			"eventId": 99906,
			"resultList": "17:1002",
			"condition": "",
			"nextEvent": []
		},
		{
			"eventId": 99907,
			"resultList": "17:3007,1:30301-1",
			"condition": "",
			"nextEvent": []
		},
		{
			"eventId": 99908,
			"resultList": "17:2007,1:30302-1",
			"condition": "",
			"nextEvent": []
		},
		{
			"eventId": 99909,
			"resultList": "17:1007,1:30303-1",
			"condition": "",
			"nextEvent": []
		},
		{
			"eventId": 99910,
			"resultList": "17:3008,1:30401-0",
			"condition": "",
			"nextEvent": []
		},
		{
			"eventId": 99911,
			"resultList": "17:2008,1:30402-0",
			"condition": "",
			"nextEvent": []
		},
		{
			"eventId": 99912,
			"resultList": "17:1008,1:30403-0",
			"condition": "",
			"nextEvent": []
		},
		{
			"eventId": 99913,
			"resultList": "17:3009",
			"condition": "",
			"nextEvent": []
		},
		{
			"eventId": 99914,
			"resultList": "17:2009",
			"condition": "",
			"nextEvent": []
		},
		{
			"eventId": 99915,
			"resultList": "17:1009",
			"condition": "",
			"nextEvent": []
		},
		{
			"eventId": 99916,
			"resultList": "17:3010",
			"condition": "",
			"nextEvent": []
		},
		{
			"eventId": 99917,
			"resultList": "17:2010",
			"condition": "",
			"nextEvent": []
		},
		{
			"eventId": 99918,
			"resultList": "17:1010",
			"condition": "",
			"nextEvent": []
		},
		{
			"eventId": 99919,
			"resultList": "17:3011,20:30501",
			"condition": "",
			"nextEvent": []
		},
		{
			"eventId": 99920,
			"resultList": "17:2011,20:30502",
			"condition": "",
			"nextEvent": []
		},
		{
			"eventId": 99921,
			"resultList": "17:1011,20:30503",
			"condition": "",
			"nextEvent": []
		},
		{
			"eventId": 99922,
			"condition": "16:1321030-1",
			"resultList": "3:123",
			"nextEvent": []
		},
		{
			"eventId": 99923,
			"nextEvent": [
				99924
			],
			"resultList": "1:90012-0,1:90011-0",
			"condition": ""
		},
		{
			"eventId": 99924,
			"condition": "19",
			"nextEvent": [
				99923
			],
			"resultList": ""
		},
		{
			"eventId": 4001001,
			"nextEvent": [
				4001002
			],
			"resultList": "23:4001005-1",
			"condition": ""
		},
		{
			"eventId": 4001002,
			"condition": "13:4001005",
			"resultList": "24:4001005-1",
			"nextEvent": []
		},
		{
			"eventId": 4001101,
			"nextEvent": [
				4001102
			],
			"resultList": "23:4001074-1",
			"condition": ""
		},
		{
			"eventId": 4001102,
			"condition": "13:4001074",
			"resultList": "24:4001074-1",
			"nextEvent": []
		},
		{
			"eventId": 4002001,
			"nextEvent": [
				4002002
			],
			"resultList": "23:4002061-1",
			"condition": ""
		},
		{
			"eventId": 4002002,
			"condition": "13:4002061",
			"resultList": "24:4002061-1",
			"nextEvent": []
		},
		{
			"eventId": 4003001,
			"condition": "14:4",
			"resultList": "23:4003009-0",
			"nextEvent": []
		},
		{
			"eventId": 4003010,
			"condition": "14:3",
			"resultList": "24:4003009-0,23:4003016-1",
			"nextEvent": []
		},
		{
			"eventId": 4003099,
			"condition": "13:4003016",
			"resultList": "24:4003016-1,22:4003067-1,60",
			"nextEvent": []
		},
		{
			"eventId": 4006001,
			"nextEvent": [
				4006002
			],
			"resultList": "23:4006018-1",
			"condition": ""
		},
		{
			"eventId": 4006002,
			"condition": "13:4006018",
			"resultList": "24:4006018-1",
			"nextEvent": []
		},
		{
			"eventId": 4006101,
			"nextEvent": [
				4006102
			],
			"resultList": "23:4006070-1",
			"condition": ""
		},
		{
			"eventId": 4006102,
			"condition": "13:4006070",
			"resultList": "24:4006070-1",
			"nextEvent": []
		},
		{
			"eventId": 4007001,
			"nextEvent": [
				4007002
			],
			"resultList": "23:4007068-1",
			"condition": ""
		},
		{
			"eventId": 4007002,
			"condition": "13:4007068",
			"resultList": "24:4007068-1",
			"nextEvent": []
		},
		{
			"eventId": 4008001,
			"nextEvent": [
				4008002
			],
			"resultList": "23:4008059-1",
			"condition": ""
		},
		{
			"eventId": 4008002,
			"condition": "13:4008059",
			"resultList": "24:4008059-1",
			"nextEvent": []
		},
		{
			"eventId": 4009001,
			"nextEvent": [
				4009002
			],
			"resultList": "23:4009051-1",
			"condition": ""
		},
		{
			"eventId": 4009002,
			"condition": "13:4009051",
			"resultList": "24:4009051-1",
			"nextEvent": []
		},
		{
			"eventId": 4010001,
			"nextEvent": [
				4010002
			],
			"resultList": "23:4010050-1",
			"condition": ""
		},
		{
			"eventId": 4010002,
			"condition": "13:4010050",
			"resultList": "24:4010050-1",
			"nextEvent": []
		},
		{
			"eventId": 4011001,
			"nextEvent": [
				4011002
			],
			"resultList": "23:4011078-1",
			"condition": ""
		},
		{
			"eventId": 4011002,
			"condition": "13:4011078",
			"resultList": "24:4011078-1",
			"nextEvent": []
		},
		{
			"eventId": 4012001,
			"nextEvent": [
				4012002
			],
			"resultList": "23:4012061-1",
			"condition": ""
		},
		{
			"eventId": 4012002,
			"condition": "13:4012061",
			"resultList": "24:4012061-1",
			"nextEvent": []
		},
		{
			"eventId": 4013001,
			"nextEvent": [
				4013002
			],
			"resultList": "23:4013092-1",
			"condition": ""
		},
		{
			"eventId": 4013002,
			"condition": "13:4013092",
			"resultList": "24:4013092-1",
			"nextEvent": []
		},
		{
			"eventId": 4017001,
			"nextEvent": [
				4017002
			],
			"resultList": "23:4017001-1",
			"condition": ""
		},
		{
			"eventId": 4017002,
			"condition": "13:4017001",
			"resultList": "24:4017001-1",
			"nextEvent": []
		},
		{
			"eventId": 4017101,
			"nextEvent": [
				4017102
			],
			"resultList": "23:4017008-1",
			"condition": ""
		},
		{
			"eventId": 4017102,
			"condition": "13:4017008",
			"resultList": "24:4017008-1",
			"nextEvent": []
		},
		{
			"eventId": 4018001,
			"nextEvent": [
				4018002
			],
			"resultList": "23:4018077-1",
			"condition": ""
		},
		{
			"eventId": 4018002,
			"condition": "13:4018077",
			"resultList": "24:4018077-1",
			"nextEvent": []
		},
		{
			"eventId": 4022001,
			"nextEvent": [
				4022002
			],
			"resultList": "23:4022047-1",
			"condition": ""
		},
		{
			"eventId": 4022002,
			"condition": "13:4022047",
			"resultList": "24:4022047-1",
			"nextEvent": []
		},
		{
			"eventId": 4022101,
			"nextEvent": [
				4022102
			],
			"resultList": "23:4022055-1",
			"condition": ""
		},
		{
			"eventId": 4022102,
			"condition": "13:4022055",
			"resultList": "24:4022055-1",
			"nextEvent": []
		},
		{
			"eventId": 4022201,
			"nextEvent": [
				4022202
			],
			"resultList": "23:4022090-1",
			"condition": ""
		},
		{
			"eventId": 4022202,
			"condition": "13:4022090",
			"resultList": "24:4022090-1",
			"nextEvent": []
		},
		{
			"eventId": 4022301,
			"nextEvent": [
				4022302
			],
			"resultList": "23:4022001-1",
			"condition": ""
		},
		{
			"eventId": 4022302,
			"condition": "13:4022001",
			"resultList": "24:4022001-1",
			"nextEvent": []
		},
		{
			"eventId": 4023001,
			"nextEvent": [
				4023002
			],
			"resultList": "23:4023001-1",
			"condition": ""
		},
		{
			"eventId": 4023002,
			"condition": "13:4023001",
			"resultList": "24:4023001-1",
			"nextEvent": []
		},
		{
			"eventId": 4023101,
			"nextEvent": [
				4023102
			],
			"resultList": "23:4023059-1",
			"condition": ""
		},
		{
			"eventId": 4023102,
			"condition": "13:4023059",
			"resultList": "24:4023059-1",
			"nextEvent": []
		},
		{
			"eventId": 4025001,
			"nextEvent": [
				4025002
			],
			"resultList": "23:4025027-1",
			"condition": ""
		},
		{
			"eventId": 4025002,
			"condition": "13:4025027",
			"resultList": "24:4025027-1",
			"nextEvent": []
		},
		{
			"eventId": 4031001,
			"condition": "14:4",
			"resultList": "23:4031007-0",
			"nextEvent": []
		},
		{
			"eventId": 4031002,
			"condition": "13:4031007",
			"resultList": "24:4031007-0,23:4031014-0",
			"nextEvent": []
		},
		{
			"eventId": 4031003,
			"condition": "14:6",
			"resultList": "24:4031007-0",
			"nextEvent": []
		},
		{
			"eventId": 4031011,
			"condition": "14:6",
			"resultList": "23:4031014-0",
			"nextEvent": []
		},
		{
			"eventId": 4031012,
			"condition": "13:4031014",
			"resultList": "24:4031014-0,23:4031016-0",
			"nextEvent": []
		},
		{
			"eventId": 4031013,
			"condition": "14:7",
			"resultList": "24:4031014-0",
			"nextEvent": []
		},
		{
			"eventId": 4031021,
			"condition": "14:7",
			"resultList": "23:4031016-0",
			"nextEvent": []
		},
		{
			"eventId": 4031022,
			"condition": "13:4031016",
			"resultList": "24:4031016-0,23:4031027-0",
			"nextEvent": []
		},
		{
			"eventId": 4031023,
			"condition": "14:9",
			"resultList": "24:4031016-0",
			"nextEvent": []
		},
		{
			"eventId": 4031031,
			"condition": "14:9",
			"resultList": "23:4031027-0",
			"nextEvent": []
		},
		{
			"eventId": 4031032,
			"condition": "13:4031027",
			"resultList": "24:4031027-0,23:4031049-1",
			"nextEvent": []
		},
		{
			"eventId": 4031033,
			"condition": "14:12",
			"resultList": "24:4031027-0,23:4031049-1,60",
			"nextEvent": []
		},
		{
			"eventId": 4031099,
			"condition": "13:4031049",
			"resultList": "24:4031049-1",
			"nextEvent": []
		},
		{
			"eventId": 4032001,
			"nextEvent": [
				4032002
			],
			"resultList": "13:4032011-1",
			"condition": ""
		},
		{
			"eventId": 4032002,
			"condition": "16:4032011-1",
			"nextEvent": [
				4032003
			],
			"resultList": "14:4032011-1"
		},
		{
			"eventId": 4032003,
			"condition": "6:5",
			"resultList": "23:4033029-1",
			"nextEvent": []
		},
		{
			"eventId": 4032099,
			"condition": "13:4033029",
			"resultList": "24:4033029-1",
			"nextEvent": []
		},
		{
			"eventId": 4035001,
			"nextEvent": [
				4035002
			],
			"resultList": "23:4035001-1",
			"condition": ""
		},
		{
			"eventId": 4035002,
			"condition": "13:4035001",
			"resultList": "24:4035001-1",
			"nextEvent": []
		},
		{
			"eventId": 4036001,
			"nextEvent": [
				4036002
			],
			"resultList": "23:4036001-1",
			"condition": ""
		},
		{
			"eventId": 4036002,
			"condition": "13:4036001",
			"resultList": "24:4036001-1",
			"nextEvent": []
		},
		{
			"eventId": 4037001,
			"nextEvent": [
				4037002
			],
			"resultList": "23:4037036-1",
			"condition": ""
		},
		{
			"eventId": 4037002,
			"condition": "13:4037036",
			"resultList": "24:4037036-1",
			"nextEvent": []
		},
		{
			"eventId": 4038001,
			"nextEvent": [
				4038002,
				4038003
			],
			"resultList": "23:4038001-1",
			"condition": ""
		},
		{
			"eventId": 4038002,
			"condition": "13:4038001",
			"resultList": "24:4038001-1",
			"nextEvent": []
		},
		{
			"eventId": 4038003,
			"condition": "14:7",
			"resultList": "23:4038001-1,60",
			"nextEvent": []
		},
		{
			"eventId": 4039001,
			"nextEvent": [
				4039002,
				4039003
			],
			"resultList": "23:4039001-1",
			"condition": ""
		},
		{
			"eventId": 4039002,
			"condition": "13:4039001",
			"resultList": "24:4039001-1",
			"nextEvent": []
		},
		{
			"eventId": 4039003,
			"condition": "14:4",
			"resultList": "23:4039001-1,60",
			"nextEvent": []
		}
	]
}