{
	"data": [
		{
			"stageid": 30481,
			"activityId": 68012,
			"unlockTime": 0
		},
		{
			"stageid": 30482,
			"activityId": 68012,
			"unlockTime": 2
		},
		{
			"stageid": 30483,
			"activityId": 68012,
			"unlockTime": 4
		},
		{
			"stageid": 30484,
			"activityId": 68012,
			"unlockTime": 6
		},
		{
			"stageid": 30485,
			"activityId": 68012,
			"unlockTime": 8
		},
		{
			"stageid": 30581,
			"activityId": 60040,
			"unlockTime": 0
		},
		{
			"stageid": 30582,
			"activityId": 60040,
			"unlockTime": 2
		},
		{
			"stageid": 30583,
			"activityId": 60040,
			"unlockTime": 4
		},
		{
			"stageid": 30584,
			"activityId": 60040,
			"unlockTime": 6
		},
		{
			"stageid": 30585,
			"activityId": 60040,
			"unlockTime": 8
		},
		{
			"stageid": 30781,
			"activityId": 60060,
			"unlockTime": 0
		},
		{
			"stageid": 30782,
			"activityId": 60060,
			"unlockTime": 2
		},
		{
			"stageid": 30783,
			"activityId": 60060,
			"unlockTime": 4
		},
		{
			"stageid": 30784,
			"activityId": 60060,
			"unlockTime": 6
		},
		{
			"stageid": 30785,
			"activityId": 60060,
			"unlockTime": 8
		},
		{
			"stageid": 30856,
			"activityId": 60073,
			"unlockTime": 0
		},
		{
			"stageid": 30857,
			"activityId": 60073,
			"unlockTime": 1
		},
		{
			"stageid": 30858,
			"activityId": 60073,
			"unlockTime": 2
		},
		{
			"stageid": 30859,
			"activityId": 60073,
			"unlockTime": 3
		},
		{
			"stageid": 30860,
			"activityId": 60073,
			"unlockTime": 4
		},
		{
			"stageid": 30891,
			"activityId": 60072,
			"unlockTime": 0
		},
		{
			"stageid": 30892,
			"activityId": 60072,
			"unlockTime": 2
		},
		{
			"stageid": 30893,
			"activityId": 60072,
			"unlockTime": 4
		},
		{
			"stageid": 30894,
			"activityId": 60072,
			"unlockTime": 6
		},
		{
			"stageid": 30895,
			"activityId": 60072,
			"unlockTime": 8
		},
		{
			"stageid": 30991,
			"activityId": 60086,
			"unlockTime": 0
		},
		{
			"stageid": 30992,
			"activityId": 60086,
			"unlockTime": 1
		},
		{
			"stageid": 30993,
			"activityId": 60086,
			"unlockTime": 2
		},
		{
			"stageid": 30994,
			"activityId": 60086,
			"unlockTime": 3
		},
		{
			"stageid": 30995,
			"activityId": 60086,
			"unlockTime": 4
		},
		{
			"stageid": 31091,
			"activityId": 60093,
			"unlockTime": 0
		},
		{
			"stageid": 31092,
			"activityId": 60093,
			"unlockTime": 1
		},
		{
			"stageid": 31093,
			"activityId": 60093,
			"unlockTime": 2
		},
		{
			"stageid": 31094,
			"activityId": 60093,
			"unlockTime": 3
		},
		{
			"stageid": 31095,
			"activityId": 60093,
			"unlockTime": 4
		},
		{
			"stageid": 31156,
			"activityId": 60105,
			"unlockTime": 0
		},
		{
			"stageid": 31157,
			"activityId": 60105,
			"unlockTime": 1
		},
		{
			"stageid": 31158,
			"activityId": 60105,
			"unlockTime": 2
		},
		{
			"stageid": 31159,
			"activityId": 60105,
			"unlockTime": 3
		},
		{
			"stageid": 31160,
			"activityId": 60105,
			"unlockTime": 4
		},
		{
			"stageid": 31291,
			"activityId": 60205,
			"unlockTime": 0
		},
		{
			"stageid": 31292,
			"activityId": 60205,
			"unlockTime": 1
		},
		{
			"stageid": 31293,
			"activityId": 60205,
			"unlockTime": 2
		},
		{
			"stageid": 31294,
			"activityId": 60205,
			"unlockTime": 3
		},
		{
			"stageid": 31295,
			"activityId": 60205,
			"unlockTime": 4
		},
		{
			"stageid": 31356,
			"activityId": 60304,
			"unlockTime": 0
		},
		{
			"stageid": 31357,
			"activityId": 60304,
			"unlockTime": 1
		},
		{
			"stageid": 31358,
			"activityId": 60304,
			"unlockTime": 2
		},
		{
			"stageid": 31359,
			"activityId": 60304,
			"unlockTime": 3
		},
		{
			"stageid": 31360,
			"activityId": 60304,
			"unlockTime": 4
		},
		{
			"stageid": 31491,
			"activityId": 60407,
			"unlockTime": 0
		},
		{
			"stageid": 31492,
			"activityId": 60407,
			"unlockTime": 1
		},
		{
			"stageid": 31493,
			"activityId": 60407,
			"unlockTime": 2
		},
		{
			"stageid": 31494,
			"activityId": 60407,
			"unlockTime": 3
		},
		{
			"stageid": 31495,
			"activityId": 60407,
			"unlockTime": 4
		},
		{
			"stageid": 31556,
			"activityId": 60507,
			"unlockTime": 0
		},
		{
			"stageid": 31557,
			"activityId": 60507,
			"unlockTime": 1
		},
		{
			"stageid": 31558,
			"activityId": 60507,
			"unlockTime": 2
		},
		{
			"stageid": 31559,
			"activityId": 60507,
			"unlockTime": 3
		},
		{
			"stageid": 31560,
			"activityId": 60507,
			"unlockTime": 4
		},
		{
			"stageid": 31691,
			"activityId": 60604,
			"unlockTime": 0
		},
		{
			"stageid": 31692,
			"activityId": 60604,
			"unlockTime": 1
		},
		{
			"stageid": 31693,
			"activityId": 60604,
			"unlockTime": 2
		},
		{
			"stageid": 31694,
			"activityId": 60604,
			"unlockTime": 3
		},
		{
			"stageid": 31695,
			"activityId": 60604,
			"unlockTime": 4
		},
		{
			"stageid": 31756,
			"activityId": 60707,
			"unlockTime": 0
		},
		{
			"stageid": 31757,
			"activityId": 60707,
			"unlockTime": 1
		},
		{
			"stageid": 31758,
			"activityId": 60707,
			"unlockTime": 2
		},
		{
			"stageid": 31759,
			"activityId": 60707,
			"unlockTime": 3
		},
		{
			"stageid": 31760,
			"activityId": 60707,
			"unlockTime": 4
		},
		{
			"stageid": 31892,
			"activityId": 60806,
			"unlockTime": 1
		},
		{
			"stageid": 31893,
			"activityId": 60806,
			"unlockTime": 2
		},
		{
			"stageid": 31894,
			"activityId": 60806,
			"unlockTime": 3
		},
		{
			"stageid": 31895,
			"activityId": 60806,
			"unlockTime": 4
		},
		{
			"stageid": 31956,
			"activityId": 60903,
			"unlockTime": 0
		},
		{
			"stageid": 31957,
			"activityId": 60903,
			"unlockTime": 1
		},
		{
			"stageid": 31958,
			"activityId": 60903,
			"unlockTime": 2
		},
		{
			"stageid": 31959,
			"activityId": 60903,
			"unlockTime": 3
		},
		{
			"stageid": 31960,
			"activityId": 60903,
			"unlockTime": 4
		},
		{
			"stageid": 32091,
			"activityId": 61009,
			"unlockTime": 0
		},
		{
			"stageid": 32092,
			"activityId": 61009,
			"unlockTime": 1
		},
		{
			"stageid": 32093,
			"activityId": 61009,
			"unlockTime": 2
		},
		{
			"stageid": 32094,
			"activityId": 61009,
			"unlockTime": 3
		},
		{
			"stageid": 32095,
			"activityId": 61009,
			"unlockTime": 4
		}
	]
}